dateitil/__init__.py
dateitil/main.py
python_dateitil-0.1.2.dist-info/METADATA
python_dateitil-0.1.2.dist-info/WHEEL
python_dateitil-0.1.2.dist-info/top_level.txt
python_dateitil-0.1.2.dist-info/RECORD
