Metadata-Version: 2.4
Name: python-dateitil
Version: 0.1.2
Summary: Demo package to simulate typosquatting (for education only)
Home-page: https://github.com/yourgithub/reqeusts-demo
Author: Your Name
Author-email: your@email.com
Classifier: Programming Language :: Python :: 3
Classifier: License :: OSI Approved :: MIT License
Classifier: Intended Audience :: Education
Classifier: Topic :: Security
Requires-Python: >=3.6
Dynamic: author
Dynamic: author-email
Dynamic: classifier
Dynamic: description
Dynamic: description-content-type
Dynamic: home-page
Dynamic: requires-python
Dynamic: summary
